{"filename": "src/fiveoutofnine.sol", "patch": "@@ -13,7 +13,7 @@ import { fiveoutofnineART } from \"./fiveoutofnineART.sol\";\n /// @author fiveoutofnine\n /// @notice This file has few docstrings (by choice) because most of it is standard. Refer to\n /// {Chess}, {Engine}, and {fiveoutofnineART} for thorough documentation.\n-contract fiveoutofnine is ERC721, Ownable, ReentrancyGuard {\n+contract fiveoutofnine is ERC721, Ownable {\n     using Chess for uint256;\n     using Strings for uint256;\n ", "project_link": "https://github.com/fiveoutofnine/fiveoutofnine-chess/commit/44e06ea20721a40950565cfc79523c4ed377e800", "solc_version": "0.8.6", "packages": "", "bug_version": {"raw_code": "", "flattened_code": "", "commit_id": "c8729720f21f0d6d80ac2d0952e39084c4344005"}, "fixed_version": {"raw_code": "", "flattened_code": "", "commit_id": "44e06ea20721a40950565cfc79523c4ed377e800"}}